funcpipe/__init__.py
funcpipe/py.typed
funcpipe-0.3.0.dist-info/LICENSE
funcpipe-0.3.0.dist-info/METADATA
funcpipe-0.3.0.dist-info/WHEEL
funcpipe-0.3.0.dist-info/RECORD
