Metadata-Version: 2.1
Name: funcpipe
Version: 0.3.0
Summary: 
Author: Lucas Silva
Author-email: lucas76leonardo@gmail.com
Requires-Python: >=3.8,<4.0
Classifier: Programming Language :: Python :: 3
Classifier: Programming Language :: Python :: 3.8
Classifier: Programming Language :: Python :: 3.9
Classifier: Programming Language :: Python :: 3.10
Classifier: Programming Language :: Python :: 3.11
